klembord/__init__.py
klembord/winclipboard.py
klembord/xclipboard.py
klembord-0.3.0.dist-info/LICENSE
klembord-0.3.0.dist-info/WHEEL
klembord-0.3.0.dist-info/METADATA
klembord-0.3.0.dist-info/RECORD
