Metadata-Version: 2.1
Name: klembord
Version: 0.3.0
Summary: Full toolkit agnostic cross-platform clipboard access
Home-page: https://github.com/OzymandiasTheGreat/klembord
License: MIT
Keywords: clipboard,cross-platform
Author: Ozymandias
Author-email: tomas.rav@gmail.com
Requires-Python: >=3.6,<4.0
Classifier: Development Status :: 5 - Production/Stable
Classifier: Environment :: Win32 (MS Windows)
Classifier: Environment :: X11 Applications
Classifier: Intended Audience :: Developers
Classifier: License :: OSI Approved :: MIT License
Classifier: Operating System :: Microsoft :: Windows
Classifier: Operating System :: POSIX
Classifier: Operating System :: POSIX :: Linux
Classifier: Programming Language :: Python :: 3
Classifier: Programming Language :: Python :: 3.10
Classifier: Programming Language :: Python :: 3.6
Classifier: Programming Language :: Python :: 3.7
Classifier: Programming Language :: Python :: 3.8
Classifier: Programming Language :: Python :: 3.9
Requires-Dist: python-xlib (>=0.26,<0.27); sys_platform == "linux"
Requires-Dist: stopit (>=1.1.2,<2.0.0); sys_platform == "linux"
Project-URL: Repository, https://github.com/OzymandiasTheGreat/klembord
